dataweave/__init__.py
dataweave/mask.py
dataweave/polygon.py
dataweave/rle.py
dataweave/utils.py
dataweave-1.2.0.dist-info/LICENSE
dataweave-1.2.0.dist-info/METADATA
dataweave-1.2.0.dist-info/WHEEL
dataweave-1.2.0.dist-info/entry_points.txt
dataweave-1.2.0.dist-info/top_level.txt
dataweave-1.2.0.dist-info/RECORD
