Metadata-Version: 2.1
Name: dataweave
Version: 1.2.0
Summary: A package for data manipulation, it has different functions e.g: encode/decode RLE, POLYGON manipulation, etc...
Home-page: https://github.com/Rtsil/dataweave
Author: Tsilavo Tahina Rakotoarisoa
Author-email: rtsilavotahina@gmail.com
Classifier: Programming Language :: Python :: 3
Classifier: License :: OSI Approved :: MIT License
Classifier: Operating System :: OS Independent
Requires-Python: >=3.6
License-File: LICENSE
Requires-Dist: numpy
Requires-Dist: opencv-python
